.hgignore
.hgtags
README
licence.html
setup.py
update.py
cjktools_data.egg-info/PKG-INFO
cjktools_data.egg-info/SOURCES.txt
cjktools_data.egg-info/dependency_links.txt
cjktools_data.egg-info/not-zip-safe
cjktools_data.egg-info/top_level.txt
data/__init__.py
data/__version__.py
data/jp_gazetteer
data/kanjd212
data/kanjidic
data/radkfile
data/dict/ce_cedict
data/dict/je_compdic
data/dict/je_edict
data/dict/je_enamdict
data/dict/je_jplaces
data/lists/char/ch_common_char_level1
data/lists/char/ch_common_char_level2
data/lists/char/ch_gb2312
data/lists/char/ch_gb2312_level1
data/lists/char/jp_common_char_jinmeiyo
data/lists/char/jp_common_char_joyo
data/lists/char/jp_full
data/lists/char/jp_jinmeiyo_variant
data/lists/char/jp_jinmeiyou
data/lists/char/jp_jis
data/lists/char/jp_jlpt_2
data/lists/char/jp_jlpt_3
data/lists/char/jp_jlpt_4
data/lists/char/jp_jyouyou
data/lists/char/jp_kanken_10
data/lists/char/jp_kanken_5
data/lists/char/jp_kanken_6
data/lists/char/jp_kanken_7
data/lists/char/jp_kanken_8
data/lists/char/jp_kanken_9
data/lists/char/jp_sjis
data/lists/word/ch_han_word_list
data/lists/word/ch_han_word_list_conv
data/lists/word/ch_han_word_list_sharedChar
data/lists/word/ch_word_list_cedict
data/lists/word/jp_han_word_list
data/lists/word/jp_han_word_list_conv
data/lists/word/jp_han_word_list_sharedChar
data/lists/word/jp_word_list_edict
data/lists/word/shared_ch_jp
data/lists/word/shared_ch_jpconv
data/lists/word/shared_jp_chconv
data/tables/gbk_pinyin_table
data/tables/zhuyin_pinyin_conv_table