Metadata-Version: 1.0
Name: cjktools-data
Version: 0.2.1-2010-07-29
Summary: A collection of Japanese data files from the EDRDG.
Home-page: http://bitbucket.org/lars512/cjktools-data/
Author: Lars Yencken
Author-email: lljy@csse.unimelb.edu.au
License: UNKNOWN
Download-URL: http://files.gakusha.info/index.html
Platform: UNKNOWN
